charz_net/__init__.py
charz_net/_client.py
charz_net/_server.py
charz_net/_socket_setup.py
charz_net-0.1.0.dev0.dist-info/METADATA
charz_net-0.1.0.dev0.dist-info/WHEEL
charz_net-0.1.0.dev0.dist-info/licenses/LICENSE
charz_net-0.1.0.dev0.dist-info/RECORD
