Metadata-Version: 2.3
Name: charz-net
Version: 0.1.0.dev0
Summary: Networking addon for charz
Author-email: Havsalt <77575424+Havsalt@users.noreply.github.com>
License: MIT License
Requires-Python: >=3.10
Requires-Dist: charz-core==0.1.0.dev2
